web3auth/__init__.py
web3auth/auth.py
web3auth/exceptions.py
web3auth/token.py
web3auth/types.py
web3auth/utils.py
web3auth-1.4.0.dist-info/LICENSE
web3auth-1.4.0.dist-info/WHEEL
web3auth-1.4.0.dist-info/METADATA
web3auth-1.4.0.dist-info/RECORD
