Metadata-Version: 2.1
Name: web3auth
Version: 1.4.0
Summary: A web3-based authentication library for python
License: GNU GENERAL PUBLIC LICENSE
Author: Павел Жуков
Author-email: 33721692+LeaveMyYard@users.noreply.github.com
Requires-Python: >=3.8,<4.0
Classifier: License :: Other/Proprietary License
Classifier: Programming Language :: Python :: 3
Classifier: Programming Language :: Python :: 3.10
Classifier: Programming Language :: Python :: 3.8
Classifier: Programming Language :: Python :: 3.9
Requires-Dist: eip712-structs (>=1.1.0,<2.0.0)
Requires-Dist: eth-account (>=0.5.6,<0.6.0)
Requires-Dist: eth-utils (>=1.9.5,<2.0.0)
Requires-Dist: python-jose[cryptography] (>=3.3.0,<4.0.0)
